magic_foundation/__init__.py
magic_foundation/logging_service.py
magic_foundation/websocket_service.py
magic_foundation-0.1.6.dist-info/LICENSE
magic_foundation-0.1.6.dist-info/METADATA
magic_foundation-0.1.6.dist-info/WHEEL
magic_foundation-0.1.6.dist-info/top_level.txt
magic_foundation-0.1.6.dist-info/RECORD
