Metadata-Version: 2.1
Name: magic-foundation
Version: 0.1.6
Summary: Minimalistic library that simplifies the adoption of async/await (asyncio) programming style in a multithreaded application.
Home-page: https://github.com/ceppelli/magic_foundation
Author: Luca Ceppelli
Author-email: luca@ceppelli.com
License: BSD 3-clause "New" or "Revised License"
Project-URL: CI: travis, https://travis-ci.com/github/ceppelli/magic_foundation
Project-URL: Coverage: codecov, https://codecov.io/github/ceppelli/magic_foundation
Project-URL: GitHub: issues, https://github.com/ceppelli/magic_foundation/issues
Project-URL: GitHub: repo, https://github.com/ceppelli/magic_foundation
Platform: UNKNOWN
Classifier: Development Status :: 4 - Beta
Classifier: Intended Audience :: Developers
Classifier: Topic :: Software Development :: Libraries
Classifier: Framework :: AsyncIO
Classifier: Programming Language :: Python :: 3
Classifier: License :: OSI Approved :: BSD License
Classifier: Operating System :: OS Independent
Classifier: Programming Language :: Python :: 3.7
Classifier: Programming Language :: Python :: 3.8
Requires-Python: >=3.7
